libusbsio/__init__.py
libusbsio/__main__.py
libusbsio/libusbsio.py
libusbsio/bin/BSD-3-clause.txt
libusbsio/bin/LICENSE-hidapi-bsd.txt
libusbsio/bin/Win32/libusbsio.dll
libusbsio/bin/linux_aarch64/libusbsio.so
libusbsio/bin/linux_armv7l/libusbsio.so
libusbsio/bin/linux_i686/libusbsio.so
libusbsio/bin/linux_x86_64/libusbsio.so
libusbsio/bin/osx_arm64/libusbsio.dylib
libusbsio/bin/osx_x86_64/libusbsio.dylib
libusbsio/bin/x64/libusbsio.dll
libusbsio-2.1.12.dist-info/METADATA
libusbsio-2.1.12.dist-info/WHEEL
libusbsio-2.1.12.dist-info/top_level.txt
libusbsio-2.1.12.dist-info/RECORD
