Metadata-Version: 2.1
Name: libusbsio
Version: 2.1.12
Summary: Python wrapper around NXP LIBUSBSIO library
Home-page: UNKNOWN
Author: Michal Hanak
Author-email: michal.hanak@nxp.com
License: BSD-3-Clause
Project-URL: NXP LIBUSBSIO Home, https://www.nxp.com/design/software/development-software/library-for-windows-macos-and-ubuntu-linux:LIBUSBSIO
Project-URL: MCULink Pro, https://www.nxp.com/design/microcontrollers-developer-resources/mcu-link-pro-debug-probe:MCU-LINK-PRO
Project-URL: LPCLink2, https://www.nxp.com/design/microcontrollers-developer-resources/lpc-microcontroller-utilities/lpc-link2:OM13054
Keywords: LIBUSBSIO,USBSIO,SPI,I2C,GPIO
Platform: Windows
Platform: Linux
Platform: Mac OSX
Classifier: Programming Language :: Python :: 3
Classifier: Operating System :: POSIX :: Linux
Classifier: Operating System :: Microsoft :: Windows
Classifier: Operating System :: MacOS :: MacOS X
Classifier: License :: OSI Approved :: BSD License
Classifier: Topic :: Scientific/Engineering
Classifier: Topic :: Software Development :: Embedded Systems
Classifier: Topic :: System :: Hardware
Classifier: Topic :: Utilities
Requires-Python: >=3.6
